DataTransfer/DataManager.py
DataTransfer/__init__.py
DataTransfer/data_transfer.py
DataTransfer/main.py
Server/ErrorHandler.py
Server/ServerHandler.py
Server/ServerMain.py
Server/__init__.py
TestID/__init__.py
TestID/newTest.py
TestID/test_id.py
HALdata-0.1.25.dist-info/METADATA
HALdata-0.1.25.dist-info/WHEEL
HALdata-0.1.25.dist-info/top_level.txt
HALdata-0.1.25.dist-info/RECORD
