Metadata-Version: 2.1
Name: HALdata
Version: 0.1.25
Summary: Transfering Data between s3, snowflake & Domo with server integration
Home-page: https://github.com/colaso96/HALdata
Author: Cole Crescas
Author-email: <colecrescas@gmail.com>
License: UNKNOWN
Platform: UNKNOWN
Classifier: Programming Language :: Python :: 3
Classifier: License :: OSI Approved :: MIT License
Classifier: Operating System :: OS Independent
Requires-Python: >=3.6
Requires-Dist: pandas
Requires-Dist: numpy
Requires-Dist: botocore
Requires-Dist: boto3
